[
  {
    "created": "2022-06-23",
    "username": "tarsolan",
    "email": "tars@tars.com",
    "phone": "12345",
    "token": "6c05f22f",
    "expires": "2022-06-26",
    "confirmed": "tbd"
  },
  {
    "created": "2022-06-23",
    "username": "Lead Lichen",
    "email": "aridgeley@msn.com",
    "phone": "7095670540",
    "token": "61703929",
    "expires": "2022-06-22",
    "confirmed": "tbd"
  },
  {
    "created": "2022-06-23",
    "username": "Mike",
    "email": "mike@mike.com",
    "phone": "1234567890",
    "token": "b4ed88e8",
    "expires": "2022-06-26",
    "confirmed": true
  },
  {
    "created": "2022-06-23",
    "username": "many",
    "email": "aridgeley@msn.com",
    "phone": "7095670540",
    "token": "73bade64",
    "expires": "2022-06-26",
    "confirmed": true
  }
]